gPCE_model/__init__.py
gPCE_model/gpc_basis.py
gPCE_model/gpc_model.py
gPCE_model/multiindex.py
gpce_model-0.1.3.dist-info/licenses/LICENSE
gpce_model-0.1.3.dist-info/METADATA
gpce_model-0.1.3.dist-info/WHEEL
gpce_model-0.1.3.dist-info/top_level.txt
gpce_model-0.1.3.dist-info/RECORD
