Metadata-Version: 2.4
Name: gPCE_model
Version: 0.1.3
Summary: Implementing generalized Polynomial Chaos Expansion (gPCE) for uncertainty quantification and surrogate modeling
Home-page: https://github.com/TRACE-Structures/gPCE_model/
Author: András Urbanics, Bence Popovics, Emese Vastag, Elmar Zander, Noémi Friedman
Author-email: popbence@hun-ren.sztaki.hu
Classifier: Programming Language :: Python :: 3
Classifier: License :: OSI Approved :: GNU General Public License v3 (GPLv3)
Classifier: Operating System :: OS Independent
Classifier: Development Status :: 3 - Alpha
License-File: LICENSE
Requires-Dist: numpy
Requires-Dist: scikit-learn
Requires-Dist: scipy
Requires-Dist: uncertain_variables
Requires-Dist: shap
Requires-Dist: pandas
Dynamic: author
Dynamic: author-email
Dynamic: classifier
Dynamic: description
Dynamic: description-content-type
Dynamic: home-page
Dynamic: license-file
Dynamic: requires-dist
Dynamic: summary
